textx_ls_core/__init__.py
textx_ls_core/exceptions.py
textx_ls_core/models.py
textx_ls_core/utils.py
textx_ls_core/features/__init__.py
textx_ls_core/features/generators.py
textx_ls_core/features/projects.py
textx_ls_core/features/validate.py
textx_ls_core-0.2.0.dist-info/METADATA
textx_ls_core-0.2.0.dist-info/WHEEL
textx_ls_core-0.2.0.dist-info/top_level.txt
textx_ls_core-0.2.0.dist-info/RECORD
